terminalizer2asciinema/__init__.py
terminalizer2asciinema/cli.py
terminalizer2asciinema/terminalizer2asciinema.py
terminalizer2asciinema/util.py
terminalizer2asciinema-0.3.0.dist-info/METADATA
terminalizer2asciinema-0.3.0.dist-info/WHEEL
terminalizer2asciinema-0.3.0.dist-info/entry_points.txt
terminalizer2asciinema-0.3.0.dist-info/licenses/LICENSE
terminalizer2asciinema-0.3.0.dist-info/RECORD
